zhplot/__init__.py
zhplot/matplotlib.py
zhplot/py.typed
zhplot/wordcloud.py
zhplot/fonts/NotoSansSC-Regular.ttf
zhplot/fonts/OFL.txt
zhplot/fonts/README.txt
zhplot-1.0.0.dist-info/LICENSE
zhplot-1.0.0.dist-info/METADATA
zhplot-1.0.0.dist-info/WHEEL
zhplot-1.0.0.dist-info/top_level.txt
zhplot-1.0.0.dist-info/zip-safe
zhplot-1.0.0.dist-info/RECORD
