Metadata-Version: 2.1
Name: zhplot
Version: 1.0.0
Summary:  一行代码搞定Python图表中文展示(Show Chinese in Figures with one line code)
Author-email: Xiangzhuang Shen <datahonor@gmail.com>
License: MIT
Project-URL: Homepage, https://shenxiangzhuang.github.io/zhplot
Project-URL: Bug Tracker, https://shenxiangzhuang.github.io/zhplot/issues
Project-URL: Documentation, https://shenxiangzhuang.github.io/zhplot
Project-URL: Source Code, https://github.com/shenxiangzhuang/zhplot
Project-URL: Release Notes, https://shenxiangzhuang.github.io/zhplot/changelog/
Classifier: Development Status :: 5 - Production/Stable
Classifier: Intended Audience :: Science/Research
Classifier: Intended Audience :: Developers
Classifier: License :: OSI Approved :: MIT License
Classifier: Operating System :: OS Independent
Classifier: Framework :: Matplotlib
Classifier: Programming Language :: Python :: 3.9
Classifier: Programming Language :: Python :: 3.10
Classifier: Programming Language :: Python :: 3.11
Classifier: Programming Language :: Python :: 3.12
Classifier: Programming Language :: Python :: 3.13
Classifier: Typing :: Typed
Requires-Python: >=3.9
License-File: LICENSE
Requires-Dist: matplotlib>=3.9.2
Provides-Extra: dev
Requires-Dist: pre-commit; extra == "dev"
Requires-Dist: ipython; extra == "dev"
Requires-Dist: black; extra == "dev"
Requires-Dist: flake8; extra == "dev"
Requires-Dist: mypy; extra == "dev"
Requires-Dist: isort; extra == "dev"
Requires-Dist: ruff; extra == "dev"
Requires-Dist: pytest; extra == "dev"
Requires-Dist: pytest-cov; extra == "dev"
Requires-Dist: pytest-sugar; extra == "dev"
Requires-Dist: hypothesis>=6.112.0; extra == "dev"
Requires-Dist: commitizen; extra == "dev"
Provides-Extra: docs
Requires-Dist: mkdocs; extra == "docs"
Requires-Dist: mkdocs-material; extra == "docs"
Requires-Dist: mkdocs-material-extensions; extra == "docs"
Requires-Dist: mkdocstrings; extra == "docs"
Requires-Dist: mkdocstrings-python; extra == "docs"
Requires-Dist: mkdocs-autorefs; extra == "docs"
Requires-Dist: mkdocs-git-committers-plugin-2; extra == "docs"
Requires-Dist: mkdocs-git-revision-date-localized-plugin; extra == "docs"
